songmam/__init__.py
songmam/api.py
songmam/exceptions.py
songmam/models/__init__.py
songmam/models/locale.py
songmam/models/messaging/__init__.py
songmam/models/messaging/message_tags.py
songmam/models/messaging/messaging_type.py
songmam/models/messaging/notification_type.py
songmam/models/messaging/payload.py
songmam/models/messaging/quick_replies.py
songmam/models/messaging/sender_action.py
songmam/models/messaging/templates/__init__.py
songmam/models/messaging/templates/airline/__init__.py
songmam/models/messaging/templates/airline/boarding_pass.py
songmam/models/messaging/templates/airline/checkin.py
songmam/models/messaging/templates/airline/flight_update.py
songmam/models/messaging/templates/airline/iternary.py
songmam/models/messaging/templates/button.py
songmam/models/messaging/templates/generic.py
songmam/models/messaging/templates/media.py
songmam/models/messaging/templates/receipt.py
songmam/models/messenger_profile/__init__.py
songmam/models/messenger_profile/get_started.py
songmam/models/messenger_profile/greeting.py
songmam/models/messenger_profile/ice_breakers.py
songmam/models/messenger_profile/persistent_menu.py
songmam/models/page.py
songmam/models/persona.py
songmam/models/send.py
songmam/models/user_profile.py
songmam/models/webhook/__init__.py
songmam/models/webhook/events/__init__.py
songmam/models/webhook/events/account_link.py
songmam/models/webhook/events/base.py
songmam/models/webhook/events/echo.py
songmam/models/webhook/events/game_play.py
songmam/models/webhook/events/handovers.py
songmam/models/webhook/events/message/__init__.py
songmam/models/webhook/events/message/attachment.py
songmam/models/webhook/events/message_deliveries.py
songmam/models/webhook/events/message_reads.py
songmam/models/webhook/events/messages.py
songmam/models/webhook/events/optin.py
songmam/models/webhook/events/policy_enforcement.py
songmam/models/webhook/events/postback.py
songmam/models/webhook/events/reaction.py
songmam/models/webhook/events/referral.py
songmam-1.10.0.dist-info/entry_points.txt
songmam-1.10.0.dist-info/LICENSE.md
songmam-1.10.0.dist-info/WHEEL
songmam-1.10.0.dist-info/METADATA
songmam-1.10.0.dist-info/RECORD
