Metadata-Version: 2.1
Name: songmam
Version: 1.10.0
Summary: a facebook messenger hypermodern python library based on fastapi. 
Home-page: https://github.com/codustry/songmam
License: MIT
Author: codustry
Author-email: hello@codustry.com
Requires-Python: >=3.8,<4.0
Classifier: Development Status :: 3 - Alpha
Classifier: Intended Audience :: Developers
Classifier: License :: OSI Approved :: MIT License
Classifier: Operating System :: OS Independent
Classifier: Programming Language :: Python :: 3
Classifier: Programming Language :: Python :: 3.8
Classifier: Programming Language :: Python :: 3.9
Classifier: Topic :: Software Development :: Libraries :: Python Modules
Requires-Dist: arrow (>=0.17,<1.2)
Requires-Dist: autoname (>=1.0.0,<2.0.0)
Requires-Dist: avajana (>=0.4,<0.5)
Requires-Dist: fastapi (>=0.61.2,<0.62.0)
Requires-Dist: furl (>=2.1.0,<3.0.0)
Requires-Dist: httpx (>=0.16.1,<0.17.0)
Requires-Dist: loguru (>=0.5.1,<0.6.0)
Requires-Dist: moshimoshi (>=0.2,<0.3)
Requires-Dist: parse (>=1.16.0,<2.0.0)
Requires-Dist: path (>=15.0.0,<16.0.0)
Project-URL: Repository, https://github.com/codustry/songmam
